rusclasp/__init__.py
rusclasp/dummy_ann.py
rusclasp/evaluation.py
rusclasp/pos_annotation.py
rusclasp/split.py
rusclasp/splitter.py
rusclasp/stupid_splitter.py
rusclasp/version.py
rusclasp/data/complex_complimentizers.json
rusclasp/data/complimentizers.json
rusclasp/data/inserted.json
rusclasp/data/inserted_evidence.json
rusclasp/data/predicates.json
rusclasp/data/prepositions.json
rusclasp/data/specificators.json
rusclasp-0.2.4.dist-info/DESCRIPTION.rst
rusclasp-0.2.4.dist-info/METADATA
rusclasp-0.2.4.dist-info/RECORD
rusclasp-0.2.4.dist-info/WHEEL
rusclasp-0.2.4.dist-info/metadata.json
rusclasp-0.2.4.dist-info/top_level.txt
