Metadata-Version: 2.0
Name: rusclasp
Version: 0.2.4
Summary: Clause splitter for Russian language.
Home-page: https://github.com/gree-gorey/rusclasp/
Author: Grigory Ignatyev
Author-email: ignatyeff.g@gmail.com
License: MIT license
Keywords: clause segmentation nlp russian
Platform: UNKNOWN
Classifier: Development Status :: 3 - Alpha
Classifier: Intended Audience :: Developers
Classifier: Intended Audience :: Science/Research
Classifier: License :: OSI Approved :: MIT License
Classifier: Natural Language :: Russian
Classifier: Programming Language :: Python
Classifier: Programming Language :: Python :: 2
Classifier: Programming Language :: Python :: 2.6
Classifier: Programming Language :: Python :: 2.7
Classifier: Topic :: Software Development :: Libraries :: Python Modules
Classifier: Topic :: Scientific/Engineering :: Information Analysis
Classifier: Topic :: Text Processing :: Linguistic
Requires: treetaggerwrapper
Requires-Dist: treetaggerwrapper
